Metadata-Version: 2.4
Name: amqstompclient
Version: 2.0.3
Summary: ActiveMQ STOMP Client for Python
Home-page: https://github.com/snuids/amqstompclient
Download-URL: https://github.com/snuids/amqstompclient/archive/2.0.2.tar.gz
Author: snuids
Author-email: snuids@mannekentech.com
Project-URL: Homepage, https://github.com/snuids/amqstompclient
Keywords: ActiveMQ,stomp,client
Requires-Python: >=3.9
License-File: LICENSE
Requires-Dist: stomp.py>=8.2.0
Dynamic: author-email
Dynamic: download-url
Dynamic: home-page
Dynamic: license-file
